mper/__init__.py
mper/cli_output.py
mper/mper.py
mper/permissions.py
mper/version_check.py
mper-1.1.1.dist-info/licenses/LICENSE
mper-1.1.1.dist-info/METADATA
mper-1.1.1.dist-info/WHEEL
mper-1.1.1.dist-info/entry_points.txt
mper-1.1.1.dist-info/top_level.txt
mper-1.1.1.dist-info/RECORD
