Metadata-Version: 2.4
Name: mper
Version: 1.1.1
Summary: Discord bot permission scanner - Analyzes discord.py code to detect required permissions and generate invite links
Author-email: FreeWiFiTech <wifi@freewifitech.jp>
Maintainer-email: FreeWiFi7749 <wifi@freewifitech.jp>
License: MIT License
Project-URL: Homepage, https://github.com/FreeWiFi7749/mper.py
Project-URL: Repository, https://github.com/FreeWiFi7749/mper.py
Project-URL: Issues, https://github.com/FreeWiFi7749/mper.py/issues
Keywords: discord,discord.py,bot,permissions,invite,scanner,ast,code-analysis
Classifier: Development Status :: 4 - Beta
Classifier: Environment :: Console
Classifier: Intended Audience :: Developers
Classifier: License :: OSI Approved :: MIT License
Classifier: Operating System :: OS Independent
Classifier: Programming Language :: Python :: 3
Classifier: Programming Language :: Python :: 3.9
Classifier: Programming Language :: Python :: 3.10
Classifier: Programming Language :: Python :: 3.11
Classifier: Programming Language :: Python :: 3.12
Classifier: Topic :: Software Development :: Libraries :: Python Modules
Classifier: Topic :: Utilities
Classifier: Typing :: Typed
Requires-Python: >=3.9
License-File: LICENSE
Requires-Dist: rich>=13.0.0
Provides-Extra: dev
Requires-Dist: ruff>=0.1.0; extra == "dev"
Requires-Dist: pytest>=7.0.0; extra == "dev"
Dynamic: license-file
